<?xml version="1.0"?>
<openerp>
	<data>
		<record model="ir.ui.view" id="account_analytic_account_form_nexan">
			<field name="name">account.analytic.account.form.nexan</field>
			<field name="model">account.analytic.account</field>
			<field name="type">tree</field>
			<field name="inherit_id" ref="analytic.view_account_analytic_account_form" />
			<field name="arch" type="xml">               
			    <field name="partner_id" position="before">
                                <field name="current" string="Current"/>
                            </field>
                        </field>
                </record>
	</data>
</openerp>
